association_quality_clavia/__init__.py
association_quality_clavia/association_quality.py
association_quality_clavia-0.3.0.dist-info/METADATA
association_quality_clavia-0.3.0.dist-info/WHEEL
association_quality_clavia-0.3.0.dist-info/licenses/LICENSE
association_quality_clavia-0.3.0.dist-info/RECORD
