Metadata-Version: 2.4
Name: association-quality-clavia
Version: 0.3.0
Summary: Enable binary classification of the association in multiple-object tracking.
Project-URL: Repository, https://github.com/kovalp/association-tracking-clavia
Project-URL: ChangeLog, https://github.com/kovalp/association-tracking-clavia/blob/main/CHANGELOG.md
Author-email: Peter Koval <pkoval@vicomtech.org>
Maintainer-email: Peter Koval <koval.peter@gmail.com>
License-File: LICENSE
Keywords: ,association quality,binary classification,tracking by detection
Requires-Python: >=3.8
